cori_ai/indexer.py
cori_ai/llm_client.py
cori_ai/review.py
cori_ai-1.2.12.dist-info/METADATA
cori_ai-1.2.12.dist-info/WHEEL
cori_ai-1.2.12.dist-info/licenses/LICENSE
cori_ai-1.2.12.dist-info/RECORD
