Metadata-Version: 2.4
Name: cori-ai
Version: 1.2.12
Summary: An AI-powered code review assistant
Project-URL: Homepage, https://github.com/theboringhumane/cori-ai
Project-URL: Repository, https://github.com/theboringhumane/cori-ai
Author-email: The Boring Human <human@theboring.human>
License-Expression: MIT
License-File: LICENSE
Classifier: Development Status :: 3 - Alpha
Classifier: Intended Audience :: Developers
Classifier: License :: OSI Approved :: MIT License
Classifier: Programming Language :: Python :: 3.12
Classifier: Topic :: Software Development :: Libraries :: Python Modules
Classifier: Topic :: Software Development :: Quality Assurance
Requires-Python: >=3.12
Requires-Dist: aiofiles==24.1.0
Requires-Dist: aiohappyeyeballs==2.4.4
Requires-Dist: aiohttp==3.11.10
Requires-Dist: aiosignal==1.3.2
Requires-Dist: annotated-types==0.7.0
Requires-Dist: anyio==4.7.0
Requires-Dist: attrs==24.3.0
Requires-Dist: cachetools==5.5.0
Requires-Dist: certifi==2024.12.14
Requires-Dist: cffi==1.17.1
Requires-Dist: charset-normalizer==3.4.0
Requires-Dist: cryptography==44.0.0
Requires-Dist: dataclasses-json==0.6.7
Requires-Dist: deprecated==1.2.15
Requires-Dist: distro==1.9.0
Requires-Dist: docutils==0.21.2
Requires-Dist: eval-type-backport==0.2.0
Requires-Dist: filelock==3.16.1
Requires-Dist: filetype==1.2.0
Requires-Dist: frozenlist==1.5.0
Requires-Dist: fsspec==2024.10.0
Requires-Dist: google-ai-generativelanguage==0.6.10
Requires-Dist: google-api-core==2.24.0
Requires-Dist: google-api-python-client==2.155.0
Requires-Dist: google-auth-httplib2==0.2.0
Requires-Dist: google-auth==2.37.0
Requires-Dist: google-generativeai==0.8.3
Requires-Dist: googleapis-common-protos==1.66.0
Requires-Dist: groq==0.13.1
Requires-Dist: grpcio-status==1.68.1
Requires-Dist: grpcio==1.68.1
Requires-Dist: h11==0.14.0
Requires-Dist: httpcore==1.0.7
Requires-Dist: httplib2==0.22.0
Requires-Dist: httpx-sse==0.4.0
Requires-Dist: httpx==0.27.2
Requires-Dist: huggingface-hub==0.27.0
Requires-Dist: idna==3.10
Requires-Dist: jaraco-classes==3.4.0
Requires-Dist: jaraco-context==6.0.1
Requires-Dist: jaraco-functools==4.1.0
Requires-Dist: jiter==0.8.2
Requires-Dist: jsonpatch==1.33
Requires-Dist: jsonpath-python==1.0.6
Requires-Dist: jsonpointer==3.0.0
Requires-Dist: keyring==25.5.0
Requires-Dist: langchain-community==0.3.12
Requires-Dist: langchain-core==0.3.28
Requires-Dist: langchain-google-genai==2.0.7
Requires-Dist: langchain-groq==0.2.1
Requires-Dist: langchain-mistralai==0.2.3
Requires-Dist: langchain-ollama==0.2.2
Requires-Dist: langchain-openai==0.2.12
Requires-Dist: langchain-text-splitters==0.3.3
Requires-Dist: langchain==0.3.12
Requires-Dist: langsmith==0.2.3
Requires-Dist: markdown-it-py==3.0.0
Requires-Dist: marshmallow==3.23.1
Requires-Dist: mdurl==0.1.2
Requires-Dist: mistralai==1.2.5
Requires-Dist: more-itertools==10.5.0
Requires-Dist: multidict==6.1.0
Requires-Dist: mypy-extensions==1.0.0
Requires-Dist: nh3==0.2.20
Requires-Dist: numpy==1.26.4
Requires-Dist: ollama==0.4.4
Requires-Dist: openai==1.55.3
Requires-Dist: orjson==3.10.12
Requires-Dist: packaging>=24.2
Requires-Dist: pkginfo==1.12.0
Requires-Dist: propcache==0.2.1
Requires-Dist: proto-plus==1.25.0
Requires-Dist: protobuf==5.29.1
Requires-Dist: pyasn1-modules==0.4.1
Requires-Dist: pyasn1==0.6.1
Requires-Dist: pycparser==2.22
Requires-Dist: pydantic-core==2.27.1
Requires-Dist: pydantic-settings==2.7.0
Requires-Dist: pydantic==2.10.3
Requires-Dist: pygithub==2.5.0
Requires-Dist: pygments==2.18.0
Requires-Dist: pyjwt==2.10.1
Requires-Dist: pynacl==1.5.0
Requires-Dist: pyparsing==3.2.0
Requires-Dist: pyproject-hooks==1.2.0
Requires-Dist: python-dateutil==2.9.0.post0
Requires-Dist: python-dotenv==1.0.1
Requires-Dist: pyyaml==6.0.2
Requires-Dist: readme-renderer==44.0
Requires-Dist: regex==2024.11.6
Requires-Dist: requests-toolbelt==1.0.0
Requires-Dist: requests==2.32.3
Requires-Dist: rfc3986==2.0.0
Requires-Dist: rich==13.9.4
Requires-Dist: rsa==4.9
Requires-Dist: setuptools==75.6.0
Requires-Dist: six==1.17.0
Requires-Dist: sniffio==1.3.1
Requires-Dist: sqlalchemy==2.0.36
Requires-Dist: tenacity==8.5.0
Requires-Dist: tiktoken==0.8.0
Requires-Dist: tokenizers==0.21.0
Requires-Dist: tqdm==4.67.1
Requires-Dist: twine==6.0.1
Requires-Dist: typing-extensions==4.12.2
Requires-Dist: typing-inspect==0.9.0
Requires-Dist: uritemplate==4.1.1
Requires-Dist: urllib3==2.2.3
Requires-Dist: wrapt==1.17.0
Requires-Dist: yarl==1.18.3
